tatsu/__init__.py
tatsu/__main__.py
tatsu/_config.py
tatsu/_version.py
tatsu/ast.py
tatsu/bootstrap.py
tatsu/buffering.py
tatsu/color.py
tatsu/contexts.py
tatsu/diagrams.py
tatsu/exceptions.py
tatsu/grammars.py
tatsu/infos.py
tatsu/leftrec.py
tatsu/model.py
tatsu/objectmodel.py
tatsu/parser.py
tatsu/parser_semantics.py
tatsu/parsing.py
tatsu/rendering.py
tatsu/semantics.py
tatsu/symtables.py
tatsu/synth.py
tatsu/tokenizing.py
tatsu/tool.py
tatsu/walkers.py
tatsu/codegen/__init__.py
tatsu/codegen/cgbase.py
tatsu/codegen/objectmodel.py
tatsu/codegen/python.py
tatsu/collections/__init__.py
tatsu/collections/orderedset.py
tatsu/collections/tail.py
tatsu/g2e/__init__.py
tatsu/g2e/__main__.py
tatsu/g2e/semantics.py
tatsu/mixins/__init__.py
tatsu/mixins/indent.py
tatsu/ngcodegen/__init__.py
tatsu/ngcodegen/objectmodel.py
tatsu/ngcodegen/python.py
tatsu/util/__init__.py
tatsu/util/_common.py
tatsu/util/boundeddict.py
tatsu/util/misc.py
tatsu/util/parproc.py
tatsu/util/testing.py
tatsu/util/unicode_characters.py
tatsu-5.14.0.dist-info/licenses/LICENSE.txt
tatsu-5.14.0.dist-info/METADATA
tatsu-5.14.0.dist-info/WHEEL
tatsu-5.14.0.dist-info/entry_points.txt
tatsu-5.14.0.dist-info/top_level.txt
tatsu-5.14.0.dist-info/RECORD
