Metadata-Version: 2.4
Name: TatSu
Version: 5.14.0
Summary: TatSu takes a grammar in a variation of EBNF as input, and outputs a memoizing PEG/Packrat parser in Python.
Author-email: Juancarlo Añez <apalala@gmail.com>
License: TATSU - A PEG/Packrat parser generator for Python
Project-URL: Homepage, https://github.com/neogeny/TatSu
Project-URL: Repository, https://github.com/neogeny/TatSu
Project-URL: Documentation, https://tatsu.readthedocs.io/en/stable/
Project-URL: Questions, https://stackoverflow.com/questions/tagged/tatsu
Classifier: Development Status :: 5 - Production/Stable
Classifier: License :: OSI Approved :: BSD License
Classifier: Natural Language :: English
Classifier: Intended Audience :: Developers
Classifier: Intended Audience :: Science/Research
Classifier: Environment :: Console
Classifier: Operating System :: OS Independent
Classifier: Programming Language :: Python :: 3.10
Classifier: Programming Language :: Python :: 3.11
Classifier: Programming Language :: Python :: 3.12
Classifier: Programming Language :: Python :: 3.13
Classifier: Programming Language :: Python :: 3.14
Classifier: Topic :: Software Development :: Code Generators
Classifier: Topic :: Software Development :: Compilers
Classifier: Topic :: Software Development :: Interpreters
Classifier: Topic :: Text Processing :: General
Requires-Python: >=3.10
License-File: LICENSE.txt
Provides-Extra: colorization
Requires-Dist: colorama; extra == "colorization"
Provides-Extra: parproc
Requires-Dist: rich; extra == "parproc"
Dynamic: license-file
